MANIFEST.in
README.md
setup.py
dobackup/__init__.py
dobackup/_dobackup
dobackup/dobackup.py
dobackup.egg-info/PKG-INFO
dobackup.egg-info/SOURCES.txt
dobackup.egg-info/dependency_links.txt
dobackup.egg-info/entry_points.txt
dobackup.egg-info/not-zip-safe
dobackup.egg-info/requires.txt
dobackup.egg-info/top_level.txt
tests/__init__.py
tests/test_dobackup.py